<?xml version="1.0" encoding="utf-8" ?>
<dwsync>
<file name="automatticons.eot" server="ftp.eleanornina.com" local="130602282323042829" remote="130536859800000000" Dst="1" />
<file name="automatticons.svg" server="ftp.eleanornina.com" local="130602267560357366" remote="130536859800000000" Dst="1" />
<file name="automatticons.ttf" server="ftp.eleanornina.com" local="130602282345027687" remote="130536859800000000" Dst="1" />
<file name="automatticons.woff" server="ftp.eleanornina.com" local="130602282321278065" remote="130536859800000000" Dst="1" />
<file name="jetpack.eot" server="ftp.eleanornina.com" local="130602282345057692" remote="130536859800000000" Dst="1" />
<file name="jetpack.ttf" server="ftp.eleanornina.com" local="130602282357086631" remote="130536859800000000" Dst="1" />
<file name="jetpack.woff" server="ftp.eleanornina.com" local="130602282346818516" remote="130536859800000000" Dst="1" />
<file name="jetpack.svg" server="ftp.eleanornina.com" local="130602267595161570" remote="130536859800000000" Dst="1" />
</dwsync>